MANIFEST.in
README.md
setup.py
root/static/README.txt
root/static/get.sh
root/static/patches/0001-upenwrt-include-target.mk-fix-Target-block-generatio.patch
upenwrt/__init__.py
upenwrt/__main__.py
upenwrt/artifact.py
upenwrt/operation.py
upenwrt/server.py
upenwrt/source.py
upenwrt/targetinfo.py
upenwrt/util.py
upenwrt/wrapio.py
upenwrt.egg-info/PKG-INFO
upenwrt.egg-info/SOURCES.txt
upenwrt.egg-info/dependency_links.txt
upenwrt.egg-info/requires.txt
upenwrt.egg-info/top_level.txt