Metadata-Version: 2.1
Name: upenwrt
Version: 0.1.1
Summary: A tool that generates custom OpenWRT sysupgrade images
Home-page: https://github.com/intelfx/upenwrt
Author: Ivan Shapovalov
Author-email: intelfx@intelfx.name
License: UNKNOWN
Platform: UNKNOWN
Classifier: Programming Language :: Python :: 3 :: Only
Classifier: Programming Language :: Python :: 3.7
Classifier: License :: OSI Approved :: GNU Affero General Public License v3
Classifier: Development Status :: 3 - Alpha
Requires-Python: >=3.7
